{
	"info": {
		"_postman_id": "84dcc540-7809-4357-9bfe-af8f3f5c78d2",
		"name": "TeamCollab",
		"schema": "https://schema.getpostman.com/json/collection/v2.1.0/collection.json"
	},
	"item": [
		{
			"name": "Role",
			"item": [
				{
					"name": "add",
					"request": {
						"method": "POST",
						"header": [],
						"body": {
							"mode": "raw",
							"raw": "{\r\n    \"name\": \"technicalLeader\",\r\n    \"description\": \"technicalLeader\"\r\n}",
							"options": {
								"raw": {
									"language": "json"
								}
							}
						},
						"url": {
							"raw": "http://localhost:3001/api/role/add",
							"protocol": "http",
							"host": [
								"localhost"
							],
							"port": "3001",
							"path": [
								"api",
								"role",
								"add"
							]
						}
					},
					"response": []
				},
				{
					"name": "get",
					"request": {
						"auth": {
							"type": "bearer",
							"bearer": [
								{
									"key": "token",
									"value": "eyJhbGciOiJIUzI1NiIsInR5cCI6IkpXVCJ9.eyJfaWQiOiI2MGNmYTQ4ZmQ5M2JhMDE1Njg5ZTY0YzAiLCJmdWxsTmFtZSI6IkNyaXN0aWFuIEdvbWV6IiwiZW1haWwiOiJjQGdtYWlsLmNvbSIsInJvbGVJZCI6IjYwY2ZhMmM1Mzc4NjMxMTJmNDhhMzU1MiIsImlhdCI6MTYyNDI4OTc4N30.9UcVX49B1RSi6GOigR_n5wnnDtr--u6AsnMtAM1JHxA",
									"type": "string"
								}
							]
						},
						"method": "GET",
						"header": [],
						"url": {
							"raw": "http://localhost:3001/api/role/get",
							"protocol": "http",
							"host": [
								"localhost"
							],
							"port": "3001",
							"path": [
								"api",
								"role",
								"get"
							]
						}
					},
					"response": []
				},
				{
					"name": "update",
					"request": {
						"auth": {
							"type": "bearer",
							"bearer": [
								{
									"key": "token",
									"value": "eyJhbGciOiJIUzI1NiIsInR5cCI6IkpXVCJ9.eyJfaWQiOiI2MGNmYTQ4ZmQ5M2JhMDE1Njg5ZTY0YzAiLCJmdWxsTmFtZSI6IkNyaXN0aWFuIEdvbWV6IiwiZW1haWwiOiJjQGdtYWlsLmNvbSIsInJvbGVJZCI6IjYwY2ZhMmM1Mzc4NjMxMTJmNDhhMzU1MiIsImlhdCI6MTYyNDI4OTAwMH0.4iScJbut70ZMKCA5VbvKsvY4OMISm3owT7SAWib5Kgc",
									"type": "string"
								}
							]
						},
						"method": "PUT",
						"header": [],
						"body": {
							"mode": "raw",
							"raw": "{\r\n    \"_id\": \"60d0a0fec26e8e0d245ba298\",\r\n    \"name\": \"scrumMaster\",\r\n    \"description\": \"scrumMaster\"\r\n}",
							"options": {
								"raw": {
									"language": "json"
								}
							}
						},
						"url": {
							"raw": "http://localhost:3001/api/role/update",
							"protocol": "http",
							"host": [
								"localhost"
							],
							"port": "3001",
							"path": [
								"api",
								"role",
								"update"
							]
						}
					},
					"response": []
				},
				{
					"name": "delete",
					"request": {
						"auth": {
							"type": "bearer",
							"bearer": [
								{
									"key": "token",
									"value": "eyJhbGciOiJIUzI1NiIsInR5cCI6IkpXVCJ9.eyJfaWQiOiI2MGNmYTQ4ZmQ5M2JhMDE1Njg5ZTY0YzAiLCJmdWxsTmFtZSI6IkNyaXN0aWFuIEdvbWV6IiwiZW1haWwiOiJjQGdtYWlsLmNvbSIsInJvbGVJZCI6IjYwY2ZhMmM1Mzc4NjMxMTJmNDhhMzU1MiIsImlhdCI6MTYyNDI4OTAwMH0.4iScJbut70ZMKCA5VbvKsvY4OMISm3owT7SAWib5Kgc",
									"type": "string"
								}
							]
						},
						"method": "PUT",
						"header": [],
						"body": {
							"mode": "raw",
							"raw": "{\r\n    \"_id\": \"60d0a0fec26e8e0d245ba298\",\r\n    \"name\": \"scrumMaster\",\r\n    \"description\": \"scrumMaster\"\r\n}",
							"options": {
								"raw": {
									"language": "json"
								}
							}
						},
						"url": {
							"raw": "http://localhost:3001/api/role/delete",
							"protocol": "http",
							"host": [
								"localhost"
							],
							"port": "3001",
							"path": [
								"api",
								"role",
								"delete"
							]
						}
					},
					"response": []
				}
			]
		},
		{
			"name": "User",
			"item": [
				{
					"name": "Add",
					"request": {
						"method": "POST",
						"header": [],
						"body": {
							"mode": "raw",
							"raw": "{\r\n    \"fullName\": \"Cristian Gomez\",\r\n    \"email\": \"c@gmail.com\",\r\n    \"password\": \"12345\"\r\n}",
							"options": {
								"raw": {
									"language": "json"
								}
							}
						},
						"url": {
							"raw": "http://localhost:3001/api/user/add",
							"protocol": "http",
							"host": [
								"localhost"
							],
							"port": "3001",
							"path": [
								"api",
								"user",
								"add"
							]
						}
					},
					"response": []
				},
				{
					"name": "GetUser",
					"request": {
						"auth": {
							"type": "bearer",
							"bearer": [
								{
									"key": "token",
									"value": "eyJhbGciOiJIUzI1NiIsInR5cCI6IkpXVCJ9.eyJfaWQiOiI2MGNmYTQ2YmQ5M2JhMDE1Njg5ZTY0YmIiLCJmdWxsTmFtZSI6IkRhbmkgdiIsImVtYWlsIjoiZEBnbWFpbC5jb20iLCJyb2xlSWQiOiI2MGNmYTJkNjM3ODYzMTEyZjQ4YTM1NTUiLCJpYXQiOjE2MjQyODg5ODB9.pgOnfLyOqeHZufbwD5Tud1FXtGOqqt3xTXcySm8n2n8",
									"type": "string"
								}
							]
						},
						"method": "GET",
						"header": [],
						"url": {
							"raw": "http://localhost:3001/api/user/getUser",
							"protocol": "http",
							"host": [
								"localhost"
							],
							"port": "3001",
							"path": [
								"api",
								"user",
								"getUser"
							]
						}
					},
					"response": []
				},
				{
					"name": "Get",
					"request": {
						"auth": {
							"type": "bearer",
							"bearer": [
								{
									"key": "token",
									"value": "eyJhbGciOiJIUzI1NiIsInR5cCI6IkpXVCJ9.eyJfaWQiOiI2MGNmYTQ4ZmQ5M2JhMDE1Njg5ZTY0YzAiLCJmdWxsTmFtZSI6IkNyaXN0aWFuIEdvbWV6IiwiZW1haWwiOiJjQGdtYWlsLmNvbSIsInJvbGVJZCI6IjYwY2ZhMmM1Mzc4NjMxMTJmNDhhMzU1MiIsImlhdCI6MTYyNDIyNTU3OX0.C7uS_GZsM8nyco5hP2DXFsQXsHJs2Ew4iSW2SlAC1rQ",
									"type": "string"
								}
							]
						},
						"method": "GET",
						"header": [],
						"url": {
							"raw": "http://localhost:3001/api/user/get",
							"protocol": "http",
							"host": [
								"localhost"
							],
							"port": "3001",
							"path": [
								"api",
								"user",
								"get"
							]
						}
					},
					"response": []
				},
				{
					"name": "AddUserAdmin",
					"request": {
						"auth": {
							"type": "bearer",
							"bearer": [
								{
									"key": "token",
									"value": "eyJhbGciOiJIUzI1NiIsInR5cCI6IkpXVCJ9.eyJfaWQiOiI2MGNmYTQ4ZmQ5M2JhMDE1Njg5ZTY0YzAiLCJmdWxsTmFtZSI6IkNyaXN0aWFuIEdvbWV6IiwiZW1haWwiOiJjQGdtYWlsLmNvbSIsInJvbGVJZCI6IjYwY2ZhMmM1Mzc4NjMxMTJmNDhhMzU1MiIsImlhdCI6MTYyNDI4NTQ3M30.1YEbrofEDSpYxM-pGCZ5Ex0njqux7i3c3nTdZgNjM5Q",
									"type": "string"
								}
							]
						},
						"method": "POST",
						"header": [],
						"body": {
							"mode": "raw",
							"raw": "{    \r\n    \"fullName\": \"Felipe perea\",\r\n    \"email\": \"f@gmail.com\",\r\n    \"password\": \"12345\",\r\n    \"roleId\": \"60d0a0fec26e8e0d245ba298\"\r\n}",
							"options": {
								"raw": {
									"language": "json"
								}
							}
						},
						"url": {
							"raw": "http://localhost:3001/api/user/addUserAdmin",
							"protocol": "http",
							"host": [
								"localhost"
							],
							"port": "3001",
							"path": [
								"api",
								"user",
								"addUserAdmin"
							]
						}
					},
					"response": []
				},
				{
					"name": "Upload",
					"request": {
						"auth": {
							"type": "bearer",
							"bearer": [
								{
									"key": "token",
									"value": "eyJhbGciOiJIUzI1NiIsInR5cCI6IkpXVCJ9.eyJfaWQiOiI2MGNmYTQ4ZmQ5M2JhMDE1Njg5ZTY0YzAiLCJmdWxsTmFtZSI6IkNyaXN0aWFuIEdvbWV6IiwiZW1haWwiOiJjQGdtYWlsLmNvbSIsInJvbGVJZCI6IjYwY2ZhMmM1Mzc4NjMxMTJmNDhhMzU1MiIsImlhdCI6MTYyNDI4NTQ3M30.1YEbrofEDSpYxM-pGCZ5Ex0njqux7i3c3nTdZgNjM5Q",
									"type": "string"
								}
							]
						},
						"method": "PUT",
						"header": [],
						"body": {
							"mode": "raw",
							"raw": "{    \r\n    \"_id\": \"60d0a17cc26e8e0d245ba2a5\",\r\n    \"fullName\": \"Felipe perez\",\r\n    \"email\": \"fe@gmail.com\",\r\n    \"password\": \"12345\",\r\n    \"roleId\": \"60d0a0fec26e8e0d245ba298\"\r\n}",
							"options": {
								"raw": {
									"language": "json"
								}
							}
						},
						"url": {
							"raw": "http://localhost:3001/api/user/update",
							"protocol": "http",
							"host": [
								"localhost"
							],
							"port": "3001",
							"path": [
								"api",
								"user",
								"update"
							]
						}
					},
					"response": []
				},
				{
					"name": "Delete",
					"request": {
						"auth": {
							"type": "bearer",
							"bearer": [
								{
									"key": "token",
									"value": "eyJhbGciOiJIUzI1NiIsInR5cCI6IkpXVCJ9.eyJfaWQiOiI2MGNmYTQ4ZmQ5M2JhMDE1Njg5ZTY0YzAiLCJmdWxsTmFtZSI6IkNyaXN0aWFuIEdvbWV6IiwiZW1haWwiOiJjQGdtYWlsLmNvbSIsInJvbGVJZCI6IjYwY2ZhMmM1Mzc4NjMxMTJmNDhhMzU1MiIsImlhdCI6MTYyNDI4NTQ3M30.1YEbrofEDSpYxM-pGCZ5Ex0njqux7i3c3nTdZgNjM5Q",
									"type": "string"
								}
							]
						},
						"method": "PUT",
						"header": [],
						"body": {
							"mode": "raw",
							"raw": "{    \r\n    \"_id\": \"60d0a17cc26e8e0d245ba2a5\",\r\n    \"fullName\": \"Felipe perez\",\r\n    \"email\": \"fe@gmail.com\",\r\n    \"password\": \"12345\",\r\n    \"roleId\": \"60d0a0fec26e8e0d245ba298\"\r\n}",
							"options": {
								"raw": {
									"language": "json"
								}
							}
						},
						"url": {
							"raw": "http://localhost:3001/api/user/delete",
							"protocol": "http",
							"host": [
								"localhost"
							],
							"port": "3001",
							"path": [
								"api",
								"user",
								"delete"
							]
						}
					},
					"response": []
				}
			]
		},
		{
			"name": "Auth",
			"item": [
				{
					"name": "login",
					"request": {
						"method": "POST",
						"header": [],
						"body": {
							"mode": "raw",
							"raw": "{\r\n    \"email\":\"c@gmail.com\",\r\n    \"password\": \"12345\"\r\n}",
							"options": {
								"raw": {
									"language": "json"
								}
							}
						},
						"url": {
							"raw": "http://localhost:3001/api/auth/login",
							"protocol": "http",
							"host": [
								"localhost"
							],
							"port": "3001",
							"path": [
								"api",
								"auth",
								"login"
							]
						}
					},
					"response": []
				}
			]
		}
	]
}